AppEnergy/__init__.py
AppEnergy/config.py
AppEnergy/main.py
AppEnergy/data_sources/__init__.py
AppEnergy/data_sources/apple_store.py
AppEnergy/data_sources/flathub.py
AppEnergy/data_sources/gog.py
AppEnergy/data_sources/itch_io.py
AppEnergy/data_sources/myabandonware.py
AppEnergy/data_sources/snap.py
AppEnergy-0.2.1.dist-info/METADATA
AppEnergy-0.2.1.dist-info/WHEEL
AppEnergy-0.2.1.dist-info/entry_points.txt
AppEnergy-0.2.1.dist-info/top_level.txt
AppEnergy-0.2.1.dist-info/RECORD
