Metadata-Version: 2.1
Name: AppEnergy
Version: 0.2.1
Requires-Dist: beautifulsoup4 ==4.13.4
Requires-Dist: Requests ==2.32.4
Requires-Dist: selenium ==4.33.0
